ecl2df/__init__.py
ecl2df/common.py
ecl2df/compdat.py
ecl2df/constants.py
ecl2df/csv2ecl.py
ecl2df/ecl2csv.py
ecl2df/eclfiles.py
ecl2df/equil.py
ecl2df/faults.py
ecl2df/fipreports.py
ecl2df/grid.py
ecl2df/gruptree.py
ecl2df/inferdims.py
ecl2df/nnc.py
ecl2df/parameters.py
ecl2df/pillars.py
ecl2df/pvt.py
ecl2df/rft.py
ecl2df/satfunc.py
ecl2df/summary.py
ecl2df/svg_color_keyword_names.txt
ecl2df/trans.py
ecl2df/version.py
ecl2df/wcon.py
ecl2df/wellcompletiondata.py
ecl2df/wellconnstatus.py
ecl2df/config_jobs/CSV2ECL
ecl2df/config_jobs/ECL2CSV
ecl2df/hook_implementations/__init__.py
ecl2df/hook_implementations/jobs.py
ecl2df/opmkeywords/BRANPROP
ecl2df/opmkeywords/COMPDAT
ecl2df/opmkeywords/COMPLUMP
ecl2df/opmkeywords/COMPSEGS
ecl2df/opmkeywords/DENSITY
ecl2df/opmkeywords/EQLDIMS
ecl2df/opmkeywords/EQUIL
ecl2df/opmkeywords/FAULTS
ecl2df/opmkeywords/GRUPNET
ecl2df/opmkeywords/GRUPTREE
ecl2df/opmkeywords/NODEPROP
ecl2df/opmkeywords/PBVD
ecl2df/opmkeywords/PDVD
ecl2df/opmkeywords/PVDG
ecl2df/opmkeywords/PVDO
ecl2df/opmkeywords/PVTG
ecl2df/opmkeywords/PVTO
ecl2df/opmkeywords/PVTW
ecl2df/opmkeywords/ROCK
ecl2df/opmkeywords/RSVD
ecl2df/opmkeywords/RVVD
ecl2df/opmkeywords/SGFN
ecl2df/opmkeywords/SGOF
ecl2df/opmkeywords/SGWFN
ecl2df/opmkeywords/SLGOF
ecl2df/opmkeywords/SOF2
ecl2df/opmkeywords/SOF3
ecl2df/opmkeywords/SWFN
ecl2df/opmkeywords/SWOF
ecl2df/opmkeywords/TABDIMS
ecl2df/opmkeywords/VFPINJ
ecl2df/opmkeywords/VFPPROD
ecl2df/opmkeywords/WCONHIST
ecl2df/opmkeywords/WCONINJE
ecl2df/opmkeywords/WCONINJH
ecl2df/opmkeywords/WCONPROD
ecl2df/opmkeywords/WELOPEN
ecl2df/opmkeywords/WELSEGS
ecl2df/opmkeywords/WELSPECS
ecl2df/opmkeywords/WLIST
ecl2df/opmkeywords/WSEGAICD
ecl2df/opmkeywords/WSEGSICD
ecl2df/opmkeywords/WSEGVALV
ecl2df/opmkeywords/readme
ecl2df/opmkeywords/runmetoupdate.sh
ecl2df/vfp/__init__.py
ecl2df/vfp/_vfp.py
ecl2df/vfp/_vfpcommon.py
ecl2df/vfp/_vfpdefs.py
ecl2df/vfp/_vfpinj.py
ecl2df/vfp/_vfpprod.py
ecl2df-0.18.0.dist-info/LICENSE
ecl2df-0.18.0.dist-info/METADATA
ecl2df-0.18.0.dist-info/WHEEL
ecl2df-0.18.0.dist-info/entry_points.txt
ecl2df-0.18.0.dist-info/top_level.txt
ecl2df-0.18.0.dist-info/RECORD
